Metadata-Version: 1.0
Name: gbdxcli
Version: 0.0.4
Summary: GBDX command line interface.
Home-page: https://github.com/DigitalGlobe/gbdxcli
Author: Donny Marino
Author-email: dmarino@digitalglobe.com
License: MIT
Platform: UNKNOWN
